customaaa/__init__.py
customaaa/assistants/__init__.py
customaaa/assistants/faq_assistant.py
customaaa-0.1.52.dist-info/METADATA
customaaa-0.1.52.dist-info/WHEEL
customaaa-0.1.52.dist-info/top_level.txt
customaaa-0.1.52.dist-info/RECORD
